ANNOUNCE-0.3.5
ANNOUNCE-0.3.6
ANNOUNCE-0.3.7
ANNOUNCE-0.4
ANNOUNCE-0.4.1
INSTALL
INSTALL-ON-WINDOWS
LICENSE
MANIFEST.in
README
TODO
setup.cfg
setup.py
tsctl
tsctl-win32.py
Toolserver/AsyncCall.py
Toolserver/Authentication.py
Toolserver/CRAMUtils.py
Toolserver/Client.py
Toolserver/ClientMachinery.py
Toolserver/ClientRegistry.py
Toolserver/Config.py
Toolserver/Context.py
Toolserver/Daemonize.py
Toolserver/DefaultConfig.py
Toolserver/Factory.py
Toolserver/HTTPHandler.py
Toolserver/LRUCache.py
Toolserver/Linda.py
Toolserver/Monitor.py
Toolserver/MonitorWin32.py
Toolserver/PickleRPCClient.py
Toolserver/ProcessQueue.py
Toolserver/RESTCall.py
Toolserver/RESTHandler.py
Toolserver/RPCHandler.py
Toolserver/ReactorChain.py
Toolserver/RewriteHandler.py
Toolserver/SOAPClient.py
Toolserver/SOAPHandler.py
Toolserver/Server.py
Toolserver/SyncCall.py
Toolserver/TagRenderer.py
Toolserver/Tool.py
Toolserver/Utils.py
Toolserver/Worker.py
Toolserver/XMLRPCClient.py
Toolserver/XMLRPCHandler.py
Toolserver/__init__.py
Toolserver/autoreload.py
Toolserver/select_trigger.py
Toolserver/timeoutsocket.py
Toolserver.egg-info/PKG-INFO
Toolserver.egg-info/SOURCES.txt
Toolserver.egg-info/dependency_links.txt
Toolserver.egg-info/requires.txt
Toolserver.egg-info/top_level.txt
samples/GreetingTool.py
samples/MailCheck.py
samples/PYXMLRPCHandler.py
samples/ServerManager.py
samples/WSGIHelloWorld.py
samples/WikiTool.py
tools/APITool.py
tools/PickleRPCHandler.py
tools/SystemTool.py
tools/WSDLTool.py
tools/WSGITool.py