Metadata-Version: 1.0
Name: Toolserver
Version: 0.4.1
Summary: Toolserver Framework for Python
Home-page: http://bitbucket.org/rfc1437/toolserver/
Author: Georg Bauer
Author-email: gb@rfc1437.de
License: MIT/X
Platform: BSD
Platform: Linux
Platform: MacOS X
Platform: win32
Classifier: Development Status :: 4 - Beta
Classifier: Intended Audience :: Developers
Classifier: License :: OSI Approved :: BSD License
Classifier: Operating System :: OS Independent
Classifier: Programming Language :: Python
Classifier: Topic :: Internet :: WWW/HTTP
